sabia_utils/__init__.py
sabia_utils/concat.py
sabia_utils/evaluate.py
sabia_utils/evaluateExperiments.py
sabia_utils/group.py
sabia_utils/pre_process.py
sabia_utils/utils/__init__.py
sabia_utils/utils/group_utils.py
sabia_utils/utils/parquet_utils.py
sabia_utils/utils/preprocess_utils.py
sabia_utils-0.2.0.dist-info/LICENSE
sabia_utils-0.2.0.dist-info/METADATA
sabia_utils-0.2.0.dist-info/WHEEL
sabia_utils-0.2.0.dist-info/top_level.txt
sabia_utils-0.2.0.dist-info/RECORD
