Metadata-Version: 2.1
Name: sabia-utils
Version: 0.2.0
Summary: Group of utilities for Sabia
Author: AI Lab Unb
Author-email: ailabunb@gmail.com
License: MIT License
Keywords: sabia utils
License-File: LICENSE
Requires-Dist: pandas (==1.4.3)
Requires-Dist: alei-utils (==0.1.3)
Requires-Dist: pyarrow (==6.0.1)
Requires-Dist: matplotlib (==3.4.3)
Requires-Dist: scikit-learn (==1.0.2)
